tracker_scraper/__init__.py
tracker_scraper/scraper.py
tracker_scraper-1.1.1.dist-info/METADATA
tracker_scraper-1.1.1.dist-info/WHEEL
tracker_scraper-1.1.1.dist-info/top_level.txt
tracker_scraper-1.1.1.dist-info/RECORD
