Metadata-Version: 2.1
Name: tracker-scraper
Version: 1.1.1
Summary: A simple torrent tracker scraper
Home-page: https://github.com/modbender/tracker-scraper
Author: Yashas H R
Author-email: rameshmamathayashas@gmail.com
Platform: any
Classifier: Environment :: Web Environment
Classifier: Intended Audience :: Developers
Classifier: Operating System :: OS Independent
Classifier: Programming Language :: Python
Classifier: Programming Language :: Python :: 3
Classifier: Programming Language :: Python :: 3 :: Only
Classifier: Topic :: Software Development :: Libraries :: Python Modules
Requires-Python: >=3.5
Requires-Dist: bencode.py
Requires-Dist: requests
